<?xml version='1.0' encoding='utf-8'?>
<pose_session start_time="2025-10-19T19:46:20.469311"><frame timestamp="2025-10-19T19:46:28.175988" elapsed_seconds="0.0"><analysis><result type="head_tilt" message="Head tilt detected (4.3)" /><result type="gesture" message="Left hand gesture detected (dist: 150.5px)" /></analysis></frame><frame timestamp="2025-10-19T19:46:28.742655" elapsed_seconds="0.6"><analysis><result type="body_tilt" message="Body asymmetry detected (1.12, 1.00)" /></analysis></frame><frame timestamp="2025-10-19T19:46:29.209322" elapsed_seconds="1.1"><analysis><result type="head_tilt" message="Head tilt detected (9.5)" /><result type="gesture" message="Left hand gesture detected (dist: 85.3px)" /></analysis></frame><frame timestamp="2025-10-19T19:46:30.342655" elapsed_seconds="2.2"><analysis><result type="head_tilt" message="Head tilt detected (5.3)" /><result type="gesture" message="Left hand gesture detected (dist: 99.2px)" /></analysis></frame><frame timestamp="2025-10-19T19:46:30.575988" elapsed_seconds="2.4"><analysis><result type="body_tilt" message="Body asymmetry detected (1.13, 1.09)" /></analysis></frame><frame timestamp="2025-10-19T19:46:31.409322" elapsed_seconds="3.3"><analysis><result type="head_tilt" message="Head tilt detected (4.0)" /><result type="gesture" message="Right hand gesture detected (dist: 166.2px)" /></analysis></frame><frame timestamp="2025-10-19T19:46:31.975988" elapsed_seconds="3.8"><analysis><result type="body_tilt" message="Body asymmetry detected (1.12, 1.08)" /></analysis></frame><frame timestamp="2025-10-19T19:46:32.575988" elapsed_seconds="4.4"><analysis><result type="gesture" message="Left hand gesture detected (dist: 189.6px)" /></analysis></frame><frame timestamp="2025-10-19T19:46:33.109322" elapsed_seconds="5.0"><analysis><result type="body_tilt" message="Body asymmetry detected (1.12, 1.13)" /></analysis></frame><frame timestamp="2025-10-19T19:46:33.675988" elapsed_seconds="5.5"><analysis><result type="gesture" message="Left hand gesture detected (dist: 177.1px)" /></analysis></frame><frame timestamp="2025-10-19T19:46:34.242655" elapsed_seconds="6.1"><analysis><result type="body_tilt" message="Body asymmetry detected (1.07, 1.17)" /></analysis></frame><frame timestamp="2025-10-19T19:46:34.842655" elapsed_seconds="6.7"><analysis><result type="gesture" message="Left hand gesture detected (dist: 175.7px)" /></analysis></frame><frame timestamp="2025-10-19T19:46:35.442655" elapsed_seconds="7.3"><analysis><result type="body_tilt" message="Body asymmetry detected (1.06, 1.18)" /></analysis></frame><frame timestamp="2025-10-19T19:46:35.975988" elapsed_seconds="7.8"><analysis><result type="gesture" message="Left hand gesture detected (dist: 173.4px)" /></analysis></frame><frame timestamp="2025-10-19T19:46:36.542655" elapsed_seconds="8.4"><analysis><result type="body_tilt" message="Body asymmetry detected (1.12, 1.17)" /></analysis></frame><frame timestamp="2025-10-19T19:46:36.875988" elapsed_seconds="8.7"><analysis><result type="head_tilt" message="Head tilt detected (4.5)" /></analysis></frame><frame timestamp="2025-10-19T19:46:37.109322" elapsed_seconds="9.0"><analysis><result type="gesture" message="Right hand gesture detected (dist: 157.3px)" /></analysis></frame><frame timestamp="2025-10-19T19:46:38.242655" elapsed_seconds="10.1"><analysis><result type="gesture" message="Left hand gesture detected (dist: 212.5px)" /></analysis></frame><frame timestamp="2025-10-19T19:46:38.609322" elapsed_seconds="10.5"><analysis><result type="body_tilt" message="Body asymmetry detected (1.11, 1.00)" /></analysis></frame><frame timestamp="2025-10-19T19:46:39.342655" elapsed_seconds="11.2"><analysis><result type="gesture" message="Left hand gesture detected (dist: 179.4px)" /></analysis></frame><frame timestamp="2025-10-19T19:46:40.442655" elapsed_seconds="12.3"><analysis><result type="gesture" message="Left hand gesture detected (dist: 183.1px)" /></analysis></frame><frame timestamp="2025-10-19T19:46:40.575988" elapsed_seconds="12.4"><analysis><result type="body_tilt" message="Body asymmetry detected (1.05, 1.17)" /></analysis></frame><frame timestamp="2025-10-19T19:46:41.509322" elapsed_seconds="13.4"><analysis><result type="gesture" message="Left hand gesture detected (dist: 191.3px)" /></analysis></frame><frame timestamp="2025-10-19T19:46:42.575988" elapsed_seconds="14.4"><analysis><result type="gesture" message="Left hand gesture detected (dist: 189.7px)" /></analysis></frame></pose_session>